{
    "files": [
        {
            "url": "gdrive:15HpLxIcSPa2STSVX5bh7CSWpwY9tWyzA#Fortnite Base [010025400AECE000][v0].nsp",
            "size": 5792315
        },
        {
            "url": "gdrive:1wpF6teSagv6441WHi_xdWGURRkUf2Xh7#Fortnite 5.40 [UPD][010025400aece800][v1179648].nsp",
            "size": 4506157862
        },
        {
            "url": "gdrive:1w0py6BytxDatYycl6rOj9nKbMCPdIHUW#Fortnite 8.51 [UPD][010025400AECE800][v3735552].nsp",
            "size": 5072691648
        }
    ],
    "directories": [""],
    "success": "Welcome to the Fortnite Switch NSP Tinfoil Shop \nPLACEHOLDER SECOND LINE"
}
